Metadata-Version: 2.1
Name: esp32-micropython-i2cLCD
Version: 0.0.1
Summary: uma biblioteca para utilização de um display i2c no esp32 micropython
Home-page: UNKNOWN
Author: issei momonge
Author-email: mggyggf@gmail.com
License: MIT License
Keywords: esp32 micropython i2c LCD
Platform: UNKNOWN
License-File: LICENCE
